orange3_ollama-0.0.3.dist-info/licenses/LICENSE
orangecontrib/__init__.py
orangecontrib/ollama/__init__.py
orangecontrib/ollama/widgets/__init__.py
orangecontrib/ollama/widgets/owollama_analysis_suggester.py
orangecontrib/ollama/widgets/owollama_script_generator.py
orangecontrib/ollama/widgets/owollama_sentiment_analyzer.py
orangecontrib/ollama/widgets/owollama_summarizer.py
orangecontrib/ollama/widgets/owollama_text_classifier.py
orangecontrib/ollama/widgets/icons/ollama-code.svg
orangecontrib/ollama/widgets/icons/ollama-idea.svg
orangecontrib/ollama/widgets/icons/ollama-label.svg
orangecontrib/ollama/widgets/icons/ollama-orange.svg
orangecontrib/ollama/widgets/icons/ollama-sentiment.svg
orangecontrib/ollama/widgets/icons/ollama-summary.svg
orange3_ollama-0.0.3.dist-info/METADATA
orange3_ollama-0.0.3.dist-info/WHEEL
orange3_ollama-0.0.3.dist-info/entry_points.txt
orange3_ollama-0.0.3.dist-info/top_level.txt
orange3_ollama-0.0.3.dist-info/RECORD
