Metadata-Version: 2.4
Name: orange3-ollama
Version: 0.0.3
Summary: A collection of Orange3 widgets that leverage Ollama to perform various data mining tasks
Author-email: Chris Lee <github@chrislee.dhs.org>
License: CC-BY-NC-SA-4.0
Project-URL: Homepage, https://github.com/chrislee35/orange3-ollama
Keywords: orange3 add-on
Classifier: Development Status :: 3 - Alpha
Classifier: Intended Audience :: Education
Classifier: Intended Audience :: Science/Research
Classifier: Programming Language :: Python :: 3 :: Only
Requires-Python: >=3.11
License-File: LICENSE
Requires-Dist: Orange3>=3.34.0
Requires-Dist: orange-canvas-core>=0.1.28
Requires-Dist: orange-widget-base>=4.20.0
Requires-Dist: requests>=2.32.3
Provides-Extra: test
Requires-Dist: coverage; extra == "test"
Provides-Extra: doc
Requires-Dist: sphinx; extra == "doc"
Requires-Dist: recommonmark; extra == "doc"
Requires-Dist: sphinx_rtd_theme; extra == "doc"
Dynamic: license-file
